ec4py/__init__.py
ec4py/cv_data.py
ec4py/cv_datas.py
ec4py/ec_data.py
ec4py/ec_datas.py
ec4py/ec_setup.py
ec4py/eis_data.py
ec4py/eis_datas.py
ec4py/lsv_data.py
ec4py/lsv_datas.py
ec4py/step_data.py
ec4py/step_datas.py
ec4py/util.py
ec4py/util_graph.py
ec4py/analysis/__init__.py
ec4py/analysis/analysis_levich.py
ec4py/analysis/analysis_ran_sev.py
ec4py/analysis/analysis_rate.py
ec4py/analysis/analysis_tafel.py
ec4py/ec_util/__init__.py
ec4py/ec_util/ec_data_base.py
ec4py/ec_util/ec_data_tdms.py
ec4py/ec_util/ec_data_txt.py
ec4py/ec_util/ec_data_util.py
ec4py/method_util/__init__.py
ec4py/method_util/ec_datas_util.py
ec4py/method_util/util_array.py
ec4py/method_util/util_data.py
ec4py/method_util/util_eis.py
ec4py/method_util/util_step.py
ec4py/method_util/util_voltammetry.py
ec4py-0.7.6.dist-info/METADATA
ec4py-0.7.6.dist-info/WHEEL
ec4py-0.7.6.dist-info/licenses/LICENSE
ec4py-0.7.6.dist-info/RECORD
