Metadata-Version: 2.4
Name: EC4py
Version: 0.7.6
Summary: A package for data treatment of electrochemical data generated by EC4 DAQ. 
Project-URL: Homepage, https://nordicec.github.io/EC4py/
Project-URL: Documentation, https://nordicec.github.io/EC4py/
Project-URL: Repository, https://github.com/nordicec/EC4py
Project-URL: Issues, https://github.com/nordicec/EC4py/issues
Project-URL: Changelog, https://github.com/NordicEC/EC4py/blob/main/CHANGELOG.md
Author-email: Gustav Wiberg <g.wiberg@nordicec.com>
Maintainer-email: Gustav Wiberg <g.wiberg@nordicec.com>
License: MIT License
License-File: LICENSE
Keywords: EC4,Nordic Electorchemistry,electorchemistry,python,tdms
Classifier: Development Status :: 4 - Beta
Classifier: Operating System :: OS Independent
Classifier: Programming Language :: Python
Requires-Python: >=3.08
Requires-Dist: matplotlib
Requires-Dist: nptdms
Requires-Dist: numpy
Requires-Dist: pandas
Requires-Dist: pathlib
Requires-Dist: scipy
